LICENSE
MANIFEST.in
README.md
setup.py
simplejsonobject.py
simplejsonobject.egg-info/PKG-INFO
simplejsonobject.egg-info/SOURCES.txt
simplejsonobject.egg-info/dependency_links.txt
simplejsonobject.egg-info/top_level.txt