Metadata-Version: 2.1
Name: simplejsonobject
Version: 0.1.4
Summary: A simple python object extension which can easily transform to and from json with compression support
Home-page: https://gitlab.com/mozgurbayhan/simplejsonobject
Author: Mehmet Ozgur Bayhan
Author-email: mozgurbayhan@gmail.com
License: BSD
Project-URL: Bug Reports, https://gitlab.com/mozgurbayhan/simplejsonobject/issues
Project-URL: Funding, https://www.losev.org.tr/bagis/Bagis.html
Project-URL: Say Thanks!, https://gitlab.com/mozgurbayhan/simplejsonobject
Project-URL: Source, https://gitlab.com/mozgurbayhan/simplejsonobject
Keywords: json  development tracker debug
Platform: UNKNOWN
Classifier: Development Status :: 5 - Production/Stable
Classifier: License :: OSI Approved :: BSD License
Classifier: Intended Audience :: Developers
Classifier: Topic :: Database :: Front-Ends
Classifier: Programming Language :: Python :: 3.5
Classifier: Programming Language :: Python :: 3.6
Classifier: Programming Language :: Python :: 3.7
Classifier: Programming Language :: Python :: 3.8
Classifier: Programming Language :: Python :: 3.9
Requires-Python: >=3.5
